fal_avatar/__init__.py
fal_avatar/generator.py
fal_avatar/config/__init__.py
fal_avatar/config/constants.py
fal_avatar/models/__init__.py
fal_avatar/models/base.py
fal_avatar/models/fabric.py
fal_avatar/models/kling.py
fal_avatar/models/omnihuman.py
fal_image_to_image/__init__.py
fal_image_to_image/__main__.py
fal_image_to_image/generator.py
fal_image_to_image/config/__init__.py
fal_image_to_image/config/constants.py
fal_image_to_image/models/__init__.py
fal_image_to_image/models/base.py
fal_image_to_image/models/clarity.py
fal_image_to_image/models/gpt_image.py
fal_image_to_image/models/kontext.py
fal_image_to_image/models/nano_banana.py
fal_image_to_image/models/photon.py
fal_image_to_image/models/seededit.py
fal_image_to_image/utils/__init__.py
fal_image_to_image/utils/file_utils.py
fal_image_to_image/utils/validators.py
fal_image_to_video/__init__.py
fal_image_to_video/cli.py
fal_image_to_video/generator.py
fal_image_to_video/config/__init__.py
fal_image_to_video/config/constants.py
fal_image_to_video/models/__init__.py
fal_image_to_video/models/base.py
fal_image_to_video/models/hailuo.py
fal_image_to_video/models/kling.py
fal_image_to_video/models/seedance.py
fal_image_to_video/models/sora.py
fal_image_to_video/models/veo.py
fal_image_to_video/models/wan.py
fal_image_to_video/utils/__init__.py
fal_image_to_video/utils/file_utils.py
fal_image_to_video/utils/validators.py
fal_text_to_video/__init__.py
fal_text_to_video/cli.py
fal_text_to_video/generator.py
fal_text_to_video/config/__init__.py
fal_text_to_video/config/constants.py
fal_text_to_video/models/__init__.py
fal_text_to_video/models/base.py
fal_text_to_video/models/kling.py
fal_text_to_video/models/sora.py
fal_text_to_video/utils/__init__.py
fal_video_to_video/__init__.py
fal_video_to_video/__main__.py
fal_video_to_video/generator.py
fal_video_to_video/config/__init__.py
fal_video_to_video/config/constants.py
fal_video_to_video/models/__init__.py
fal_video_to_video/models/base.py
video_ai_studio-1.0.18.dist-info/METADATA
video_ai_studio-1.0.18.dist-info/WHEEL
video_ai_studio-1.0.18.dist-info/entry_points.txt
video_ai_studio-1.0.18.dist-info/top_level.txt
video_ai_studio-1.0.18.dist-info/RECORD
