Metadata-Version: 2.4
Name: video_ai_studio
Version: 1.0.18
Summary: Comprehensive AI content generation suite with multiple providers and services
Home-page: https://github.com/donghaozhang/video-agent-skill
Author: donghao zhang
Author-email: zdhpeter@gmail.com
Project-URL: Documentation, https://github.com/donghaozhang/video-agent-skill/blob/main/README.md
Project-URL: Source, https://github.com/donghaozhang/video-agent-skill
Project-URL: Tracker, https://github.com/donghaozhang/video-agent-skill/issues
Project-URL: Changelog, https://github.com/donghaozhang/video-agent-skill/blob/main/CHANGELOG.md
Keywords: ai,content generation,images,videos,audio,fal,elevenlabs,google,parallel processing,veo,pipeline
Classifier: Development Status :: 4 - Beta
Classifier: Intended Audience :: Developers
Classifier: License :: OSI Approved :: MIT License
Classifier: Operating System :: OS Independent
Classifier: Programming Language :: Python :: 3
Classifier: Programming Language :: Python :: 3.10
Classifier: Programming Language :: Python :: 3.11
Classifier: Programming Language :: Python :: 3.12
Classifier: Topic :: Software Development :: Libraries :: Python Modules
Classifier: Topic :: Scientific/Engineering :: Artificial Intelligence
Classifier: Topic :: Multimedia :: Graphics
Classifier: Topic :: Multimedia :: Video
Classifier: Topic :: Multimedia :: Sound/Audio
Requires-Python: >=3.10
Requires-Dist: python-dotenv>=1.0.0
Requires-Dist: requests>=2.31.0
Requires-Dist: typing-extensions>=4.0.0
Requires-Dist: pyyaml>=6.0
Requires-Dist: pathlib2>=2.3.7
Requires-Dist: argparse>=1.4.0
Requires-Dist: fal-client>=0.4.0
Requires-Dist: replicate>=0.15.0
Requires-Dist: openai<2.0.0,>=1.0.0
Requires-Dist: google-generativeai>=0.2.0
Requires-Dist: elevenlabs>=1.0.0
Requires-Dist: Pillow>=10.0.0
Requires-Dist: httpx>=0.25.0
Requires-Dist: aiohttp>=3.8.0
Provides-Extra: pipeline
Requires-Dist: pyyaml>=6.0; extra == "pipeline"
Requires-Dist: pathlib2>=2.3.7; extra == "pipeline"
Provides-Extra: google-cloud
Requires-Dist: google-cloud-aiplatform>=1.38.0; extra == "google-cloud"
Requires-Dist: google-cloud-storage>=2.10.0; extra == "google-cloud"
Requires-Dist: google-auth>=2.23.0; extra == "google-cloud"
Provides-Extra: video
Requires-Dist: moviepy>=1.0.3; extra == "video"
Requires-Dist: ffmpeg-python>=0.2.0; extra == "video"
Provides-Extra: image
Requires-Dist: Pillow>=10.0.0; extra == "image"
Provides-Extra: dev
Requires-Dist: pytest>=7.0.0; extra == "dev"
Requires-Dist: pytest-asyncio>=0.21.0; extra == "dev"
Requires-Dist: black>=22.0.0; extra == "dev"
Requires-Dist: flake8>=4.0.0; extra == "dev"
Requires-Dist: mypy>=1.0.0; extra == "dev"
Provides-Extra: jupyter
Requires-Dist: jupyter>=1.0.0; extra == "jupyter"
Requires-Dist: ipython>=8.0.0; extra == "jupyter"
Requires-Dist: notebook>=7.0.0; extra == "jupyter"
Requires-Dist: matplotlib>=3.5.0; extra == "jupyter"
Provides-Extra: mcp
Requires-Dist: mcp>=1.0.0; extra == "mcp"
Provides-Extra: all
Requires-Dist: jupyter>=1.0.0; extra == "all"
Requires-Dist: pathlib2>=2.3.7; extra == "all"
Requires-Dist: pytest-asyncio>=0.21.0; extra == "all"
Requires-Dist: ipython>=8.0.0; extra == "all"
Requires-Dist: flake8>=4.0.0; extra == "all"
Requires-Dist: matplotlib>=3.5.0; extra == "all"
Requires-Dist: google-cloud-aiplatform>=1.38.0; extra == "all"
Requires-Dist: google-cloud-storage>=2.10.0; extra == "all"
Requires-Dist: moviepy>=1.0.3; extra == "all"
Requires-Dist: ffmpeg-python>=0.2.0; extra == "all"
Requires-Dist: pytest>=7.0.0; extra == "all"
Requires-Dist: black>=22.0.0; extra == "all"
Requires-Dist: mypy>=1.0.0; extra == "all"
Requires-Dist: notebook>=7.0.0; extra == "all"
Requires-Dist: pyyaml>=6.0; extra == "all"
Requires-Dist: mcp>=1.0.0; extra == "all"
Requires-Dist: google-auth>=2.23.0; extra == "all"
Provides-Extra: cloud
Requires-Dist: google-cloud-storage>=2.10.0; extra == "cloud"
Requires-Dist: google-cloud-aiplatform>=1.38.0; extra == "cloud"
Requires-Dist: google-auth>=2.23.0; extra == "cloud"
Provides-Extra: media
Requires-Dist: Pillow>=10.0.0; extra == "media"
Requires-Dist: ffmpeg-python>=0.2.0; extra == "media"
Requires-Dist: moviepy>=1.0.3; extra == "media"
Dynamic: author
Dynamic: author-email
Dynamic: classifier
Dynamic: description
Dynamic: description-content-type
Dynamic: home-page
Dynamic: keywords
Dynamic: project-url
Dynamic: provides-extra
Dynamic: requires-dist
Dynamic: requires-python
Dynamic: summary
